bme280/__init__.py
bme280/bme280.py
cfredmond_bme280/__init__.py
cfredmond_bme280/bme280.py
cfredmond_bme280-0.2.0.dist-info/METADATA
cfredmond_bme280-0.2.0.dist-info/WHEEL
cfredmond_bme280-0.2.0.dist-info/top_level.txt
cfredmond_bme280-0.2.0.dist-info/RECORD
