Metadata-Version: 2.1
Name: cfredmond-bme280
Version: 0.2.0
Summary: BME280 enviornment sensor library
Home-page: UNKNOWN
Author: Charles Redmond
License: MIT
Platform: UNKNOWN
Requires-Dist: smbus2
